Metadata-Version: 2.0
Name: ak-django-oauth-toolkit
Version: 1.0.2
Summary: OAuth2 Provider for Django
Home-page: https://github.com/appknox/django-oauth-toolkit
Author: Federico Frenguelli, Massimiliano Pippi
Author-email: engineering@appknox.com
License: UNKNOWN
Download-URL: https://github.com/appknox/django-oauth-toolkit/tarball/develop
Keywords: django,oauth,oauth2,oauthlib
Platform: UNKNOWN
Classifier: Development Status :: 5 - Production/Stable
Classifier: Environment :: Web Environment
Classifier: Framework :: Django
Classifier: Framework :: Django :: 1.11
Classifier: Framework :: Django :: 2.0
Classifier: Intended Audience :: Developers
Classifier: License :: OSI Approved :: BSD License
Classifier: Operating System :: OS Independent
Classifier: Programming Language :: Python :: 2.7
Classifier: Programming Language :: Python :: 3
Classifier: Programming Language :: Python :: 3.4
Classifier: Programming Language :: Python :: 3.5
Classifier: Programming Language :: Python :: 3.6
Classifier: Topic :: Internet :: WWW/HTTP
Requires-Dist: django (>=1.11)
Requires-Dist: oauthlib (>=2.0.3)
Requires-Dist: requests (>=2.13.0)
